gradients/__init__.py
gradients/gradients.py
gradients-0.0.3.data/data/LICENSE
gradients-0.0.3.dist-info/LICENSE
gradients-0.0.3.dist-info/METADATA
gradients-0.0.3.dist-info/WHEEL
gradients-0.0.3.dist-info/top_level.txt
gradients-0.0.3.dist-info/RECORD
